twisted/plugins/mllp_plugin.py
txHL7/__init__.py
txHL7/mllp.py
txHL7/receiver.py
txHL7-0.5.0.dist-info/DESCRIPTION.rst
txHL7-0.5.0.dist-info/METADATA
txHL7-0.5.0.dist-info/RECORD
txHL7-0.5.0.dist-info/WHEEL
txHL7-0.5.0.dist-info/metadata.json
txHL7-0.5.0.dist-info/top_level.txt
